checklists_scrapers
