Metadata-Version: 1.1
Name: checklists-scrapers
Version: 0.2.1
Summary: Web scrapers for downloading checklists of birds from onlinedatabases such as eBird.
Home-page: http://pypi.python.org/pypi/checklists_scrapers/
Author: Stuart MacKay
Author-email: smackay@flagstonesoftware.com
License: GPL
Keywords: eBird worldbirds web scraper birds checklists
Platform: UNKNOWN
Classifier: Development Status :: 4 - Beta
Classifier: Environment :: Web Environment
Classifier: Intended Audience :: Science/Research
Classifier: License :: OSI Approved :: BSD License
Classifier: Operating System :: OS Independent
Classifier: Programming Language :: Python
Classifier: Natural Language :: English
Classifier: Topic :: Internet :: WWW/HTTP
